LICENSE
MANIFEST.in
README.rst
setup.cfg
setup.py
versioneer.py
artellapipe/__init__.py
artellapipe/launcher/__init__.py
artellapipe/launcher/plugins/__init__.py
artellapipe/launcher/plugins/dccselector/__init__.py
artellapipe/launcher/plugins/dccselector/__logging__.ini
artellapipe/launcher/plugins/dccselector/__version__.py
artellapipe/launcher/plugins/dccselector/_version.py
artellapipe/launcher/plugins/dccselector/dccselector.py
artellapipe/launcher/plugins/dccselector/loader.py
artellapipe/launcher/plugins/dccselector/register.py
artellapipe/launcher/plugins/dccselector/dccs/__init__.py
artellapipe/launcher/plugins/dccselector/dccs/houdinidcc.py
artellapipe/launcher/plugins/dccselector/dccs/mayadcc.py
artellapipe/launcher/plugins/dccselector/dccs/nukedcc.py
artellapipe/launcher/plugins/dccselector/dccs/photoshopdcc.py
artellapipe/launcher/plugins/dccselector/dccs/substancedesignerdcc.py
artellapipe/launcher/plugins/dccselector/dccs/substancepainterdcc.py
artellapipe/launcher/plugins/dccselector/dccs/zbrushdcc.py
artellapipe/launcher/plugins/dccselector/resources/icons/color/artella.png
artellapipe/launcher/plugins/dccselector/resources/icons/color/houdini.png
artellapipe/launcher/plugins/dccselector/resources/icons/color/launcher.png
artellapipe/launcher/plugins/dccselector/resources/icons/color/maya.png
artellapipe/launcher/plugins/dccselector/resources/icons/color/nuke.png
artellapipe/launcher/plugins/dccselector/resources/icons/color/photoshop.png
artellapipe/launcher/plugins/dccselector/resources/icons/color/substance_designer.png
artellapipe/launcher/plugins/dccselector/resources/icons/color/substance_painter.png
artellapipe/launcher/plugins/dccselector/resources/icons/color/zbrush.png
artellapipe/launcher/plugins/dccselector/resources/icons/defafult/artella.png
artellapipe/launcher/plugins/dccselector/resources/icons/defafult/houdini.png
artellapipe/launcher/plugins/dccselector/resources/icons/defafult/launcher.png
artellapipe_launcher_plugins_dccselector.egg-info/PKG-INFO
artellapipe_launcher_plugins_dccselector.egg-info/SOURCES.txt
artellapipe_launcher_plugins_dccselector.egg-info/dependency_links.txt
artellapipe_launcher_plugins_dccselector.egg-info/not-zip-safe
artellapipe_launcher_plugins_dccselector.egg-info/requires.txt
artellapipe_launcher_plugins_dccselector.egg-info/top_level.txt
