Metadata-Version: 2.1
Name: artellapipe-launcher-plugins-dccselector
Version: 0.0.11
Summary: Repository that contains source code for DCCSelector ArtellaPipe Launcher Plugin
Home-page: UNKNOWN
Author: Tomas Poveda
Author-email: tpovedatd@gmail.com
License: MIT
Platform: UNKNOWN
Provides-Extra: dev
Provides-Extra: test
